{"id":"ripple","symbol":"xrp","name":"XRP","localization":{"en":"XRP","de":"XRP","es":"XRP","fr":"XRP","it":"XRP","pl":"XRP","ro":"XRP","hu":"XRP","nl":"XRP","pt":"XRP","sv":"XRP","vi":"XRP","tr":"XRP","ru":"XRP","ja":"リップル","zh":"瑞波币","zh-tw":"瑞波幣","ko":"리플코인","ar":"XRP","th":"XRP","id":"XRP"},"image":{"thumb":"https://assets.coingecko.com/coins/images/44/thumb/xrp-symbol-white-128.png?1605778731","small":"https://assets.coingecko.com/coins/images/44/small/xrp-symbol-white-128.png?1605778731"},"market_data":{"current_price":{"aud":null,"bdt":0.40944186443486,"bhd":0.0019899650780880003,"bmd":0.005277694,"brl":null,"btc":1.163e-05,"cad":0.005827127764,"chf":0.004676823072,"cny":0.032723069325,"dkk":null,"eur":0.003814997041,"gbp":0.003141167634,"hkd":0.041130787093,"idr":null,"inr":null,"jpy":0.539529637392,"krw":5.522500517708,"ltc":0.000493214588634436,"mmk":5.08228516301852,"mxn":null,"myr":null,"ngn":0.848929213318506,"nzd":null,"php":null,"pln":null,"rub":0.19002311661,"sek":0.034937884199,"sgd":0.006666506732,"twd":0.160753239678,"uah":0.060386583093900006,"usd":0.005277694,"vef":0.03320595761297,"vnd":111.3360335830741,"xag":null,"xau":null,"xdr":0.003421975147,"zar":null},"market_cap":{"aud":null,"brl":null,"btc":null,"cad":null,"chf":null,"cny":null,"dkk":null,"eur":null,"gbp":null,"hkd":null,"idr":null,"inr":null,"jpy":null,"krw":null,"mxn":null,"myr":null,"ngn":6783394630.348625,"nzd":null,"php":null,"pln":null,"rub":null,"sek":null,"sgd":null,"twd":null,"uah":482520823.97190005,"usd":42171574.0,"vnd":889633953600.7761,"xag":null,"xau":null,"xdr":null,"zar":null},"total_volume":{"aud":11832.35747102103,"bdt":847243.8498728883,"bhd":4117.7657204130655,"bmd":10920.9491539975,"brl":24560.97158522831,"btc":24.0655556500606,"cad":12057.873386462183,"chf":9677.58778200373,"cny":67712.71245757339,"dkk":59231.12262748854,"eur":7894.241065778334,"gbp":6499.909243525038,"hkd":null,"idr":127018130.26124513,"inr":666295.4129086423,"jpy":1116429.9667682024,"krw":null,"ltc":1020.5918426658438,"mmk":10516596.424772099,"mxn":144151.2753219686,"myr":35898.85889741868,"ngn":1756659.7786826028,"nzd":12798.365720703418,"php":489995.14469198073,"pln":33406.17752185218,"rub":393208.2448474557,"sek":null,"sgd":null,"twd":332641.1036456095,"uah":124955.8620776663,"usd":10920.9491539975,"vef":68711.93644440954,"vnd":230383792.95361012,"xag":556.9226822981374,"xau":8.42294447752121,"xdr":7080.974491251316,"zar":117013.32312628719}},"community_data":{"facebook_likes":null,"twitter_followers":6314,"reddit_average_posts_48h":0.0,"reddit_average_comments_48h":0.0,"reddit_subscribers":null,"reddit_accounts_active_48h":null},"developer_data":{"forks":178,"stars":812,"subscribers":243,"total_issues":null,"closed_issues":null,"pull_requests_merged":56,"pull_request_contributors":12,"code_additions_deletions_4_weeks":{"additions":null,"deletions":null},"commit_count_4_weeks":null},"public_interest_stats":{"alexa_rank":null,"bing_matches":null}}