{"id":"ripple","symbol":"xrp","name":"XRP","localization":{"en":"XRP","de":"XRP","es":"XRP","fr":"XRP","it":"XRP","pl":"XRP","ro":"XRP","hu":"XRP","nl":"XRP","pt":"XRP","sv":"XRP","vi":"XRP","tr":"XRP","ru":"XRP","ja":"リップル","zh":"瑞波币","zh-tw":"瑞波幣","ko":"리플코인","ar":"XRP","th":"XRP","id":"XRP"},"image":{"thumb":"https://assets.coingecko.com/coins/images/44/thumb/xrp-symbol-white-128.png?1605778731","small":"https://assets.coingecko.com/coins/images/44/small/xrp-symbol-white-128.png?1605778731"},"market_data":{"current_price":{"aud":null,"bdt":0.27602905207153317,"bhd":0.00134144438799125,"bmd":0.003558604375,"brl":null,"btc":6.25e-06,"cad":0.00387071125,"chf":0.003190173125,"cny":0.022191953125,"dkk":null,"eur":0.002609129375,"gbp":0.00211177875,"hkd":0.02759112125,"idr":null,"inr":null,"jpy":0.36259508125,"krw":3.6467391324999996,"ltc":0.00030879446640316206,"mmk":3.440714929265,"mxn":null,"myr":null,"ngn":0.5775543764123544,"nzd":null,"php":null,"pln":null,"rub":0.12161615,"sek":0.023585995,"sgd":0.0044577175,"twd":0.107292523125,"uah":0.042343619941862504,"usd":0.003558604375,"vef":0.022390649762390625,"vnd":75.16365540847788,"xag":null,"xau":null,"xdr":0.002308215,"zar":null},"market_cap":{"aud":null,"brl":null,"btc":null,"cad":null,"chf":null,"cny":null,"dkk":null,"eur":null,"gbp":null,"hkd":null,"idr":null,"inr":null,"jpy":null,"krw":null,"mxn":null,"myr":null,"ngn":4625524676.610195,"nzd":null,"php":null,"pln":null,"rub":null,"sek":null,"sgd":null,"twd":null,"uah":339122110.2933,"usd":28500195.0,"vnd":601971618734.5001,"xag":null,"xau":null,"xdr":null,"zar":null},"total_volume":{"aud":9471.527000617842,"bdt":678081.9601202015,"bhd":3295.3387810991176,"bmd":8741.925575525967,"brl":19435.671071956614,"btc":15.3535007237317,"cad":9508.63487651703,"chf":7836.852061362707,"cny":54515.866938513194,"dkk":47908.8579214227,"eur":6409.483159579542,"gbp":5187.711450637796,"hkd":67779.24801287106,"idr":101277806.49989988,"inr":511273.69902476575,"jpy":890736.6147829487,"krw":8958433.905615913,"ltc":758.5721701448468,"mmk":8452323.065059943,"mxn":112662.77077813582,"myr":28106.172162115785,"ngn":1418797.045798639,"nzd":10236.019256104397,"php":381966.31786933803,"pln":26692.95458194968,"rub":298757.3835267941,"sek":57940.41460838916,"sgd":10950.651017990635,"twd":263570.53303211,"uah":104019.64790764895,"usd":8741.925575525967,"vef":55003.977173069994,"vnd":184644038.03398162,"xag":451.51421393342946,"xau":6.7678231190209335,"xdr":5670.268907684538,"zar":90359.89793072535}},"community_data":{"facebook_likes":null,"twitter_followers":6808,"reddit_average_posts_48h":0.204,"reddit_average_comments_48h":3.286,"reddit_subscribers":935,"reddit_accounts_active_48h":"14.0"},"developer_data":{"forks":185,"stars":827,"subscribers":240,"total_issues":null,"closed_issues":null,"pull_requests_merged":56,"pull_request_contributors":12,"code_additions_deletions_4_weeks":{"additions":null,"deletions":null},"commit_count_4_weeks":null},"public_interest_stats":{"alexa_rank":null,"bing_matches":null}}